0 PUSH_GLOBAL_I n
1 PUSH_GLOBAL_C res
2 DEF calcularFac
3 PUSH_LOCAL_I num_aux
4 LOAD_CONST 0
5 LOAD_FAST NUM
6 LOAD_CONST 1
7 COMPARE_OP <
8 JUMP_IF_FALSE 12
9 LOAD_CONST 1
10 STORE_FAST num_aux
11 JUMP_ABSOLUTE 20
12 LOAD_FAST num
13 LOAD_FAST num
14 LOAD_CONST 1
15 BINARY_SUBSTRACT
16 LOAD_GLOBAL calcularFac
17 CALL_FUNCTION 1
18 BINARY_MULTIPLY
19 STORE_FAST num_aux
20 LOAD_FAST num_aux
21 RETURN_VALUE
22 DEF Main
23 LOAD_CONST 5
24 STORE_GLOBAL n
25 LOAD_GLOBAL n
26 LOAD_GLOBAL calcularFac
27 CALL_FUNCTION 1
28 LOAD_CONST 70
29 STORE_GLOBAL res
30 LOAD_GLOBAL res
31 LOAD_GLOBAL write
32 CALL_FUNCTION 1
33 LOAD_CONST 58
34 LOAD_GLOBAL write
35 CALL_FUNCTION 1
36 LOAD_CONST 32
37 LOAD_GLOBAL write
38 CALL_FUNCTION 1
39 LOAD_GLOBAL res
40 LOAD_GLOBAL write
41 CALL_FUNCTION 1
42 END